{
    "gallery": [{
            "name": "Lemon",
            "codeName": "lemon",
            "cover": [
                "https://placebear.com/400/400",
                "http://placebear.com/400/400",
                "http://placebear.com/400/400"
            ],
            "private": true,
            "photos": [{
                    "src": "http://placebear.com/400/400",
                    "codeName": "lemon-1"
                },
                {
                    "src": "http://placebear.com/400/400",
                    "codeName": "lemon-2",
                    "desc": "Last time with Lemon, but I  didn't know that time."
                },
                {
                    "src": "http://placebear.com/400/400",
                    "codeName": "lemon-3"
                },
                {
                    "src": "http://placebear.com/400/400",
                    "codeName": "lemon-4"
                },
                {
                    "src": "http://placebear.com/400/400",
                    "codeName": "lemon-5"
                }
            ]
        },
        {
            "name": "Irene",
            "codeName": "irene",
            "cover": [
                "http://placebear.com/400/400",
                "http://placebear.com/400/400",
                "http://placebear.com/400/400"
            ],
            "private": false,
            "photos": [{
                    "src": "http://placebear.com/400/400",
                    "codeName": "irene-1"
                },
                {
                    "src": "http://placebear.com/400/400",
                    "codeName": "irene-2"
                },
                {
                    "src": "http://placebear.com/400/400",
                    "codeName": "irene-3"
                }
            ]
        },
        {
            "name": "Ivy",
            "codeName": "Ivy",
            "cover": [
                "http://placebear.com/400/400",
                "http://placebear.com/400/400",
                "http://placebear.com/400/400"
            ],
            "private": false,
            "photos": [{
                    "src": "http://placebear.com/400/400",
                    "codeName": "Ivy-1"
                },
                {
                    "src": "http://placebear.com/400/400",
                    "codeName": "Ivy-2"
                },
                {
                    "src": "http://placebear.com/400/400",
                    "codeName": "Ivy-3"
                }
            ]
        }
    ]
}